{
  "data": {
    "mods": {
      "facetsData": {
        "gameId": {
          "100": 11
        }
      },
      "nodes": [
        {
          "adultContent": false,
          "createdAt": "2025-04-13T19:33:27Z",
          "downloads": 128,
          "endorsements": 5,
          "fileSize": 14119,
          "game": {
            "domainName": "morrowind",
            "id": 100,
            "name": "Morrowind"
          },
          "modCategory": {
            "categoryId": 24,
            "name": "User Interface"
          },
          "modId": 56352,
          "name": "Siltstrider Main Menu Replacer",
          "status": "published",
          "summary": "Graphic created by Polion in 2020 and all credits go to him.I just converted his art to work as a Morrowind main menu replacer.",
          "thumbnailUrl": "https://staticdelivery.nexusmods.com/mods/100/images/thumbnails/56352/56352-1744575176-1275248238.jpeg",
          "thumbnailBlurredUrl": "https://images.nexusmods.com/mod-images/100/tb/med/56/56352/56352-1744575176-1275248238.jpeg",
          "uid": "429496785952",
          "updatedAt": "2025-04-13T19:33:27Z",
          "uploader": {
            "avatar": "https://avatars.nexusmods.com/81751823/100",
            "memberId": 81751823,
            "name": "Demanufacturer87"
          },
          "viewerDownloaded": null,
          "viewerEndorsed": null,
          "viewerTracked": false,
          "viewerUpdateAvailable": null,
          "isBlockedFromEarningDp": null,
          "viewerBlocked": false
        },
        {
          "adultContent": false,
          "createdAt": "2024-08-06T20:48:38Z",
          "downloads": 822,
          "endorsements": 40,
          "fileSize": 4429,
          "game": {
            "domainName": "morrowind",
            "id": 100,
            "name": "Morrowind"
          },
          "modCategory": {
            "categoryId": 3,
            "name": "Dungeons and Locations"
          },
          "modId": 55073,
          "name": "Dwemer Legacy Reforged - Bthungthumz and Druscashti",
          "status": "published",
          "summary": "Cinematic overhaul of obsolete dwemer ruins: Bthungthumz and Druscashti. Will you dare to enter this kingdom of ruin and search for ancient treasures? Will you dare to interrupt",
          "thumbnailUrl": "https://staticdelivery.nexusmods.com/mods/100/images/thumbnails/55073/55073-1724430255-696716890.png",
          "thumbnailBlurredUrl": "https://images.nexusmods.com/mod-images/100/tb/med/55/55073/55073-1724430255-696716890.png",
          "uid": "429496784673",
          "updatedAt": "2024-09-29T21:40:07Z",
          "uploader": {
            "avatar": "https://avatars.nexusmods.com/81751823/100",
            "memberId": 81751823,
            "name": "Demanufacturer87"
          },
          "viewerDownloaded": null,
          "viewerEndorsed": null,
          "viewerTracked": false,
          "viewerUpdateAvailable": null,
          "isBlockedFromEarningDp": null,
          "viewerBlocked": false
        },
        {
          "adultContent": false,
          "createdAt": "2024-06-07T15:38:47Z",
          "downloads": 3804,
          "endorsements": 78,
          "fileSize": 28191,
          "game": {
            "domainName": "morrowind",
            "id": 100,
            "name": "Morrowind"
          },
          "modCategory": {
            "categoryId": 3,
            "name": "Dungeons and Locations"
          },
          "modId": 54807,
          "name": "Dwemer Legacy Reforged - Arkngthunch-Sturdumz",
          "status": "published",
          "summary": "Expansive overhaul for Dwemer Ruins of Arkngthunch-Sturdumz (exteriors with new interiors) inspired by ESO and my imagination ( ͡° ͜ʖ ͡°)My mod does not alter original",
          "thumbnailUrl": "https://staticdelivery.nexusmods.com/mods/100/images/thumbnails/54807/54807-1717773490-397979101.jpeg",
          "thumbnailBlurredUrl": "https://images.nexusmods.com/mod-images/100/tb/med/54/54807/54807-1717773490-397979101.jpeg",
          "uid": "429496784407",
          "updatedAt": "2025-04-27T21:49:35Z",
          "uploader": {
            "avatar": "https://avatars.nexusmods.com/81751823/100",
            "memberId": 81751823,
            "name": "Demanufacturer87"
          },
          "viewerDownloaded": null,
          "viewerEndorsed": null,
          "viewerTracked": false,
          "viewerUpdateAvailable": null,
          "isBlockedFromEarningDp": null,
          "viewerBlocked": false
        },
        {
          "adultContent": false,
          "createdAt": "2023-12-08T23:22:05Z",
          "downloads": 96,
          "endorsements": 7,
          "fileSize": 146,
          "game": {
            "domainName": "morrowind",
            "id": 100,
            "name": "Morrowind"
          },
          "modCategory": {
            "categoryId": 36,
            "name": "Immersion"
          },
          "modId": 53810,
          "name": "Anthology Solstheim Spire",
          "status": "published",
          "summary": "My edit of Dr No's original Solstheim Mage Tower mod to work with Anthology Solstheim.",
          "thumbnailUrl": "https://staticdelivery.nexusmods.com/mods/100/images/thumbnails/53810/53810-1702077538-641036594.png",
          "thumbnailBlurredUrl": "https://images.nexusmods.com/mod-images/100/tb/med/53/53810/53810-1702077538-641036594.png",
          "uid": "429496783410",
          "updatedAt": "2023-12-08T23:22:05Z",
          "uploader": {
            "avatar": "https://avatars.nexusmods.com/81751823/100",
            "memberId": 81751823,
            "name": "Demanufacturer87"
          },
          "viewerDownloaded": null,
          "viewerEndorsed": null,
          "viewerTracked": false,
          "viewerUpdateAvailable": null,
          "isBlockedFromEarningDp": null,
          "viewerBlocked": false
        },
        {
          "adultContent": false,
          "createdAt": "2023-12-03T20:50:28Z",
          "downloads": 131,
          "endorsements": 6,
          "fileSize": 12,
          "game": {
            "domainName": "morrowind",
            "id": 100,
            "name": "Morrowind"
          },
          "modCategory": {
            "categoryId": 36,
            "name": "Immersion"
          },
          "modId": 53788,
          "name": "Mid Mushroom Overhaul x Sheogorad - Groves of the North PATCH",
          "status": "published",
          "summary": "Simple patch (plugin replacer) for Mid Mushroom Overhaul to work with Sheogorad - Groves of the North",
          "thumbnailUrl": "https://staticdelivery.nexusmods.com/mods/100/images/thumbnails/53788/53788-1701636588-1951271033.png",
          "thumbnailBlurredUrl": "https://images.nexusmods.com/mod-images/100/tb/med/53/53788/53788-1701636588-1951271033.png",
          "uid": "429496783388",
          "updatedAt": "2023-12-03T20:50:28Z",
          "uploader": {
            "avatar": "https://avatars.nexusmods.com/81751823/100",
            "memberId": 81751823,
            "name": "Demanufacturer87"
          },
          "viewerDownloaded": null,
          "viewerEndorsed": null,
          "viewerTracked": false,
          "viewerUpdateAvailable": null,
          "isBlockedFromEarningDp": null,
          "viewerBlocked": false
        },
        {
          "adultContent": false,
          "createdAt": "2023-10-18T22:06:38Z",
          "downloads": 9893,
          "endorsements": 143,
          "fileSize": 5914,
          "game": {
            "domainName": "morrowind",
            "id": 100,
            "name": "Morrowind"
          },
          "modCategory": {
            "categoryId": 3,
            "name": "Dungeons and Locations"
          },
          "modId": 53627,
          "name": "Markgran Forest (Maar Gan Forest)",
          "status": "published",
          "summary": "In The Elder Scrolls Arena there was a place called Markgran Forest (since TES III known as a Maar Gan). Discovering this fact felt very unique and interesting to me so I decided",
          "thumbnailUrl": "https://staticdelivery.nexusmods.com/mods/100/images/thumbnails/53627/53627-1697665257-668215105.png",
          "thumbnailBlurredUrl": "https://images.nexusmods.com/mod-images/100/tb/med/53/53627/53627-1697665257-668215105.png",
          "uid": "429496783227",
          "updatedAt": "2025-05-06T20:15:50Z",
          "uploader": {
            "avatar": "https://avatars.nexusmods.com/81751823/100",
            "memberId": 81751823,
            "name": "Demanufacturer87"
          },
          "viewerDownloaded": null,
          "viewerEndorsed": null,
          "viewerTracked": false,
          "viewerUpdateAvailable": null,
          "isBlockedFromEarningDp": null,
          "viewerBlocked": false
        },
        {
          "adultContent": false,
          "createdAt": "2023-05-14T12:02:15Z",
          "downloads": 1459,
          "endorsements": 32,
          "fileSize": 78,
          "game": {
            "domainName": "morrowind",
            "id": 100,
            "name": "Morrowind"
          },
          "modCategory": {
            "categoryId": 26,
            "name": "ENB Preset"
          },
          "modId": 52873,
          "name": "Royale Reshade Demanufactured - OpenMW Reshade Preset",
          "status": "published",
          "summary": "Reshade preset for OpenMW ( ͡° ͜ʖ ͡°)",
          "thumbnailUrl": "https://staticdelivery.nexusmods.com/mods/100/images/thumbnails/52873/52873-1684065132-795628575.png",
          "thumbnailBlurredUrl": "https://images.nexusmods.com/mod-images/100/tb/med/52/52873/52873-1684065132-795628575.png",
          "uid": "429496782473",
          "updatedAt": "2023-08-27T17:41:34Z",
          "uploader": {
            "avatar": "https://avatars.nexusmods.com/81751823/100",
            "memberId": 81751823,
            "name": "Demanufacturer87"
          },
          "viewerDownloaded": null,
          "viewerEndorsed": null,
          "viewerTracked": false,
          "viewerUpdateAvailable": null,
          "isBlockedFromEarningDp": null,
          "viewerBlocked": false
        },
        {
          "adultContent": false,
          "createdAt": "2022-07-17T01:47:15Z",
          "downloads": 17798,
          "endorsements": 239,
          "fileSize": 6953,
          "game": {
            "domainName": "morrowind",
            "id": 100,
            "name": "Morrowind"
          },
          "modCategory": {
            "categoryId": 36,
            "name": "Immersion"
          },
          "modId": 51615,
          "name": "Kogoruhn - Extinct City of Ash and Sulfur",
          "status": "published",
          "summary": "While wandering through the desolated landscapes of northern ashlands, Nerevarine comes across the old capital city of Chimer tribe - once known as Kogoruhn. This ancient place,",
          "thumbnailUrl": "https://staticdelivery.nexusmods.com/mods/100/images/thumbnails/51615/51615-1687541032-734153709.png",
          "thumbnailBlurredUrl": "https://images.nexusmods.com/mod-images/100/tb/med/51/51615/51615-1687541032-734153709.png",
          "uid": "429496781215",
          "updatedAt": "2025-02-22T12:22:48Z",
          "uploader": {
            "avatar": "https://avatars.nexusmods.com/81751823/100",
            "memberId": 81751823,
            "name": "Demanufacturer87"
          },
          "viewerDownloaded": null,
          "viewerEndorsed": null,
          "viewerTracked": false,
          "viewerUpdateAvailable": null,
          "isBlockedFromEarningDp": null,
          "viewerBlocked": false
        },
        {
          "adultContent": false,
          "createdAt": "2022-01-05T00:59:50Z",
          "downloads": 2294,
          "endorsements": 61,
          "fileSize": 16157,
          "game": {
            "domainName": "morrowind",
            "id": 100,
            "name": "Morrowind"
          },
          "modCategory": {
            "categoryId": 26,
            "name": "ENB Preset"
          },
          "modId": 50598,
          "name": "Shades of Demanufacturer - reshade preset for OpenMW",
          "status": "published",
          "summary": "Reshade preset by Demanufacturer87 for OpenMW.",
          "thumbnailUrl": "https://staticdelivery.nexusmods.com/mods/100/images/thumbnails/50598/50598-1641342904-877887044.png",
          "thumbnailBlurredUrl": "https://images.nexusmods.com/mod-images/100/tb/med/50/50598/50598-1641342904-877887044.png",
          "uid": "429496780198",
          "updatedAt": "2024-02-17T18:23:10Z",
          "uploader": {
            "avatar": "https://avatars.nexusmods.com/81751823/100",
            "memberId": 81751823,
            "name": "Demanufacturer87"
          },
          "viewerDownloaded": null,
          "viewerEndorsed": null,
          "viewerTracked": false,
          "viewerUpdateAvailable": null,
          "isBlockedFromEarningDp": null,
          "viewerBlocked": false
        },
        {
          "adultContent": false,
          "createdAt": "2021-02-22T10:46:10Z",
          "downloads": 1351,
          "endorsements": 75,
          "fileSize": 5923,
          "game": {
            "domainName": "morrowind",
            "id": 100,
            "name": "Morrowind"
          },
          "modCategory": {
            "categoryId": 24,
            "name": "User Interface"
          },
          "modId": 49329,
          "name": "Chaos Heart - Main Menu Replacer",
          "status": "published",
          "summary": "Main menu replacer based on The Elder Scrolls III: Morrowind Chaos Heart mod.",
          "thumbnailUrl": "https://staticdelivery.nexusmods.com/mods/100/images/thumbnails/49329/49329-1613990503-2125046282.png",
          "thumbnailBlurredUrl": "https://images.nexusmods.com/mod-images/100/tb/med/49/49329/49329-1613990503-2125046282.png",
          "uid": "429496778929",
          "updatedAt": "2023-07-16T10:37:20Z",
          "uploader": {
            "avatar": "https://avatars.nexusmods.com/81751823/100",
            "memberId": 81751823,
            "name": "Demanufacturer87"
          },
          "viewerDownloaded": null,
          "viewerEndorsed": null,
          "viewerTracked": false,
          "viewerUpdateAvailable": null,
          "isBlockedFromEarningDp": null,
          "viewerBlocked": false
        },
        {
          "adultContent": false,
          "createdAt": "2020-06-17T20:40:37Z",
          "downloads": 2943,
          "endorsements": 113,
          "fileSize": 2740,
          "game": {
            "domainName": "morrowind",
            "id": 100,
            "name": "Morrowind"
          },
          "modCategory": {
            "categoryId": 24,
            "name": "User Interface"
          },
          "modId": 48364,
          "name": "Morrowind Molten Menu - Main Menu Replacer",
          "status": "published",
          "summary": "Main menu replacer based on The Elder Scrolls Online: Morrowind menu graphic.",
          "thumbnailUrl": "https://staticdelivery.nexusmods.com/mods/100/images/thumbnails/48364/48364-1606517520-706879576.png",
          "thumbnailBlurredUrl": "https://images.nexusmods.com/mod-images/100/tb/med/48/48364/48364-1606517520-706879576.png",
          "uid": "429496777964",
          "updatedAt": "2023-08-06T08:55:13Z",
          "uploader": {
            "avatar": "https://avatars.nexusmods.com/81751823/100",
            "memberId": 81751823,
            "name": "Demanufacturer87"
          },
          "viewerDownloaded": null,
          "viewerEndorsed": null,
          "viewerTracked": false,
          "viewerUpdateAvailable": null,
          "isBlockedFromEarningDp": null,
          "viewerBlocked": false
        }
      ],
      "totalCount": 11
    }
  }
}