{
  "checkedAt": "2026-01-07T12:40:59.647Z",
  "mods": {
    "facetsData": {
      "gameId": {
        "100": 7
      }
    },
    "nodes": [
      {
        "adultContent": false,
        "createdAt": "2025-12-24T09:38:37Z",
        "fileSize": 398428,
        "modCategory": {
          "categoryId": 25,
          "name": "Audio"
        },
        "modId": 57971,
        "name": "Diverse Voices",
        "status": "published",
        "summary": "Adds voices from Oblivion and Skyrim to Morrowind (AI-generated)",
        "thumbnailUrl": "https://staticdelivery.nexusmods.com/mods/100/images/thumbnails/57971/57971-1766560640-604400511.jpg",
        "uid": "429496787571",
        "updatedAt": "2025-12-24T09:38:37Z",
        "fileIds": [
          "1000059467"
        ]
      },
      {
        "adultContent": false,
        "createdAt": "2025-08-22T20:32:13Z",
        "fileSize": 1723990,
        "modCategory": {
          "categoryId": 25,
          "name": "Audio"
        },
        "modId": 57346,
        "name": "Skyrim Home of the Nords - Fully Voiced",
        "status": "published",
        "summary": "Adds fully AI-voiced dialogue to Skyrim: Home of the Nords.",
        "thumbnailUrl": "https://staticdelivery.nexusmods.com/mods/100/images/thumbnails/57346/57346-1755889973-795162947.jpg",
        "uid": "429496786946",
        "updatedAt": "2025-08-24T09:07:20Z",
        "fileIds": [
          "1000056263",
          "1000056264",
          "1000056315",
          "1000056314",
          "1000056266",
          "1000056265"
        ]
      },
      {
        "adultContent": false,
        "createdAt": "2025-08-02T19:01:20Z",
        "fileSize": 27000,
        "modCategory": {
          "categoryId": 25,
          "name": "Audio"
        },
        "modId": 57230,
        "name": "Shipyards of Vvardenfell - Fully Voiced",
        "status": "published",
        "summary": "Adds fully AI-voiced dialogue to Shipyards of Vvardenfell.",
        "thumbnailUrl": "https://staticdelivery.nexusmods.com/mods/100/images/thumbnails/57230/57230-1754160862-628421314.jpg",
        "uid": "429496786830",
        "updatedAt": "2025-08-02T19:01:20Z",
        "fileIds": [
          "1000055621",
          "1000055619",
          "1000055620",
          "1000055618",
          "1000055617"
        ]
      },
      {
        "adultContent": false,
        "createdAt": "2025-08-02T15:59:24Z",
        "fileSize": 18891,
        "modCategory": {
          "categoryId": 25,
          "name": "Audio"
        },
        "modId": 57227,
        "name": "Ebonheart Underworks - Fully Voiced",
        "status": "published",
        "summary": "Adds fully AI-voiced dialogue to Ebonheart Underworks.",
        "thumbnailUrl": "https://staticdelivery.nexusmods.com/mods/100/images/thumbnails/57227/57227-1754149102-880220153.jpg",
        "uid": "429496786827",
        "updatedAt": "2025-08-02T15:59:24Z",
        "fileIds": [
          "1000055614",
          "1000055611",
          "1000055613",
          "1000055610",
          "1000055612"
        ]
      },
      {
        "adultContent": false,
        "createdAt": "2025-07-18T07:06:04Z",
        "fileSize": 4187030,
        "modCategory": {
          "categoryId": 25,
          "name": "Audio"
        },
        "modId": 57146,
        "name": "Project Cyrodiil - Fully Voiced",
        "status": "published",
        "summary": "Adds fully AI-voiced dialogue to Project Cyrodiil: Abecean Shores",
        "thumbnailUrl": "https://staticdelivery.nexusmods.com/mods/100/images/thumbnails/57146/57146-1755894799-1875779804.jpg",
        "uid": "429496786746",
        "updatedAt": "2025-07-18T07:06:04Z",
        "fileIds": [
          "1000055296",
          "1000055294"
        ]
      },
      {
        "adultContent": false,
        "createdAt": "2025-05-04T21:11:30Z",
        "fileSize": 3712740,
        "modCategory": {
          "categoryId": 25,
          "name": "Audio"
        },
        "modId": 56488,
        "name": "Tamriel Rebuilt - Grasping Fortune - Fully Voiced",
        "status": "published",
        "summary": "Adds fully AI-voiced dialogue to the latest release of Tamriel Rebuilt. Covers all original playable races. New TR races and creatures with dialogue will be voiced in a later update.",
        "thumbnailUrl": "https://staticdelivery.nexusmods.com/mods/100/images/thumbnails/56488/56488-1746376650-2057634310.jpeg",
        "uid": "429496786088",
        "updatedAt": "2025-05-05T09:28:53Z"
      },
      {
        "adultContent": false,
        "createdAt": "2025-04-09T18:34:08Z",
        "fileSize": 95708,
        "modCategory": {
          "categoryId": 25,
          "name": "Audio"
        },
        "modId": 56331,
        "name": "AFFresh - Fully Voiced",
        "status": "published",
        "summary": "Adds fully AI-voiced dialogue to AFFresh. Covers all playable races and even one creature.",
        "thumbnailUrl": "https://staticdelivery.nexusmods.com/mods/100/images/thumbnails/56331/56331-1752047893-1058434926.jpg",
        "uid": "429496785931",
        "updatedAt": "2025-07-09T08:15:51Z",
        "fileIds": [
          "1000055090",
          "1000055093",
          "1000055089",
          "1000055092",
          "1000055091"
        ]
      }
    ],
    "totalCount": 7
  }
}